vtlengine/API/_InternalApi.py
vtlengine/API/__init__.py
vtlengine/API/data/schema/external_routines_schema.json
vtlengine/API/data/schema/json_schema_2.1.json
vtlengine/API/data/schema/value_domain_schema.json
vtlengine/AST/ASTComment.py
vtlengine/AST/ASTConstructor.py
vtlengine/AST/ASTConstructorModules/Expr.py
vtlengine/AST/ASTConstructorModules/ExprComponents.py
vtlengine/AST/ASTConstructorModules/Terminals.py
vtlengine/AST/ASTConstructorModules/__init__.py
vtlengine/AST/ASTDataExchange.py
vtlengine/AST/ASTEncoders.py
vtlengine/AST/ASTString.py
vtlengine/AST/ASTTemplate.py
vtlengine/AST/ASTVisitor.py
vtlengine/AST/DAG/__init__.py
vtlengine/AST/DAG/_words.py
vtlengine/AST/Grammar/Vtl.g4
vtlengine/AST/Grammar/VtlTokens.g4
vtlengine/AST/Grammar/__init__.py
vtlengine/AST/Grammar/lexer.py
vtlengine/AST/Grammar/parser.py
vtlengine/AST/Grammar/tokens.py
vtlengine/AST/VtlVisitor.py
vtlengine/AST/__init__.py
vtlengine/DataTypes/TimeHandling.py
vtlengine/DataTypes/__init__.py
vtlengine/DataTypes/_time_checking.py
vtlengine/Exceptions/__exception_file_generator.py
vtlengine/Exceptions/__init__.py
vtlengine/Exceptions/messages.py
vtlengine/Interpreter/__init__.py
vtlengine/Model/__init__.py
vtlengine/Operators/Aggregation.py
vtlengine/Operators/Analytic.py
vtlengine/Operators/Assignment.py
vtlengine/Operators/Boolean.py
vtlengine/Operators/CastOperator.py
vtlengine/Operators/Clause.py
vtlengine/Operators/Comparison.py
vtlengine/Operators/Conditional.py
vtlengine/Operators/General.py
vtlengine/Operators/HROperators.py
vtlengine/Operators/Join.py
vtlengine/Operators/Numeric.py
vtlengine/Operators/RoleSetter.py
vtlengine/Operators/Set.py
vtlengine/Operators/String.py
vtlengine/Operators/Time.py
vtlengine/Operators/Validation.py
vtlengine/Operators/__init__.py
vtlengine/Utils/__Virtual_Assets.py
vtlengine/Utils/__init__.py
vtlengine/__extras_check.py
vtlengine/__init__.py
vtlengine/files/__init__.py
vtlengine/files/output/__init__.py
vtlengine-1.4.0.dist-info/METADATA
vtlengine-1.4.0.dist-info/WHEEL
vtlengine-1.4.0.dist-info/licenses/LICENSE.md
vtlengine-1.4.0.dist-info/RECORD
