Metadata-Version: 2.4
Name: vtlengine
Version: 1.4.0
Summary: Run and Validate VTL Scripts
License-Expression: AGPL-3.0
License-File: LICENSE.md
Keywords: vtl,sdmx,vtlengine,Validation and Transformation Language
Author: MeaningfulData
Author-email: info@meaningfuldata.eu
Maintainer: Francisco Javier Hernandez del Caño
Maintainer-email: javier.hernandez@meaningfuldata.eu
Requires-Python: >=3.9
Classifier: Development Status :: 5 - Production/Stable
Classifier: Intended Audience :: Developers
Classifier: Intended Audience :: Information Technology
Classifier: Intended Audience :: Science/Research
Classifier: Typing :: Typed
Provides-Extra: all
Provides-Extra: s3
Requires-Dist: antlr4-python3-runtime (>=4.9,<4.10)
Requires-Dist: duckdb (>=1.4,<1.5)
Requires-Dist: jsonschema (>=3.2.0,<5.0)
Requires-Dist: networkx (>=2.8,<3.0)
Requires-Dist: pandas (>=2.1.4,<3.0)
Requires-Dist: pysdmx[xml] (>=1.5.2,<2.0)
Requires-Dist: s3fs (>=2022.11.0) ; extra == "all"
Requires-Dist: s3fs (>=2022.11.0) ; extra == "s3"
Requires-Dist: sqlglot (>=22.2.0,<23.0)
Project-URL: Authors, https://github.com/Meaningful-Data/vtlengine/graphs/contributors
Project-URL: Documentation, https://docs.vtlengine.meaningfuldata.eu
Project-URL: IssueTracker, https://github.com/Meaningful-Data/vtlengine/issues
Project-URL: MeaningfulData, https://www.meaningfuldata.eu/
Project-URL: Repository, https://github.com/Meaningful-Data/vtlengine
